vodka/__init__.py
vodka/app.py
vodka/bartender.py
vodka/component.py
vodka/config/__init__.py
vodka/config/configurator.py
vodka/config/shared.py
vodka/config/validators.py
vodka/data/__init__.py
vodka/data/data_types.py
vodka/data/handlers.py
vodka/data/renderers.py
vodka/exceptions.py
vodka/instance.py
vodka/load_entrypoints.py
vodka/log.py
vodka/plugins/__init__.py
vodka/plugins/django.py
vodka/plugins/flask.py
vodka/plugins/wsgi.py
vodka/plugins/zeromq.py
vodka/resources/blank_app/__init__.py
vodka/resources/blank_app/application.py
vodka/resources/blank_app/plugins/__init__.py
vodka/resources/blank_app/plugins/example.py
vodka/runners/__init__.py
vodka/runners/wsgi.py
vodka/storage.py
vodka/util.py
vodka-3.2.0.dist-info/entry_points.txt
vodka-3.2.0.dist-info/LICENSE
vodka-3.2.0.dist-info/WHEEL
vodka-3.2.0.dist-info/METADATA
vodka-3.2.0.dist-info/RECORD
